dynatrace/__init__.py
dynatrace/dynatrace_object.py
dynatrace/http_client.py
dynatrace/main.py
dynatrace/pagination.py
dynatrace/utils.py
dynatrace/configuration_v1/__init__.py
dynatrace/configuration_v1/alerting_profiles.py
dynatrace/configuration_v1/anomaly_detection_process_groups.py
dynatrace/configuration_v1/dashboard.py
dynatrace/configuration_v1/endpoint.py
dynatrace/configuration_v1/extensions.py
dynatrace/configuration_v1/maintenance_windows.py
dynatrace/configuration_v1/metag.py
dynatrace/configuration_v1/metric_events.py
dynatrace/configuration_v1/notifications.py
dynatrace/configuration_v1/plugins.py
dynatrace/configuration_v1/tile.py
dynatrace/environment_v1/__init__.py
dynatrace/environment_v1/cluster_time.py
dynatrace/environment_v1/custom_device.py
dynatrace/environment_v1/event.py
dynatrace/environment_v1/smartscape_hosts.py
dynatrace/environment_v1/synthetic_monitors.py
dynatrace/environment_v1/synthetic_third_party.py
dynatrace/environment_v1/timeseries.py
dynatrace/environment_v2/__init__.py
dynatrace/environment_v2/activegates.py
dynatrace/environment_v2/activegates_autoupdate_configuration.py
dynatrace/environment_v2/activegates_autoupdate_jobs.py
dynatrace/environment_v2/audit_logs.py
dynatrace/environment_v2/metrics.py
dynatrace/environment_v2/monitored_entities.py
dynatrace/environment_v2/schemas.py
dynatrace/environment_v2/tokens_api.py
dynatrace/environment_v2/tokens_tenant.py
test/__init__.py
test/conftest.py
test/configuration_v1/__init__.py
test/configuration_v1/test_alerting_profiles.py
test/configuration_v1/test_extensions.py
test/environment_v1/__init__.py
test/environment_v1/test_smartscape_hosts.py
test/environment_v1/test_synthetic_monitors.py
test/environment_v2/__init__.py
test/environment_v2/test_activegate_autoupdate_configuration.py
test/environment_v2/test_activegate_autoupdate_jobs.py
test/environment_v2/test_audit_logs.py
test/environment_v2/test_entities.py
test/environment_v2/test_metrics.py
dtapi-1.1.26.dist-info/LICENSE
dtapi-1.1.26.dist-info/METADATA
dtapi-1.1.26.dist-info/WHEEL
dtapi-1.1.26.dist-info/top_level.txt
dtapi-1.1.26.dist-info/RECORD
